odoo/addons/l10n_es_partner_mercantil/README.rst
odoo/addons/l10n_es_partner_mercantil/__init__.py
odoo/addons/l10n_es_partner_mercantil/__manifest__.py
odoo/addons/l10n_es_partner_mercantil/i18n/bg.po
odoo/addons/l10n_es_partner_mercantil/i18n/ca.po
odoo/addons/l10n_es_partner_mercantil/i18n/es.po
odoo/addons/l10n_es_partner_mercantil/i18n/eu.po
odoo/addons/l10n_es_partner_mercantil/i18n/fr.po
odoo/addons/l10n_es_partner_mercantil/i18n/gl.po
odoo/addons/l10n_es_partner_mercantil/i18n/hr.po
odoo/addons/l10n_es_partner_mercantil/i18n/l10n_es_partner_mercantil.pot
odoo/addons/l10n_es_partner_mercantil/i18n/nl.po
odoo/addons/l10n_es_partner_mercantil/i18n/pt.po
odoo/addons/l10n_es_partner_mercantil/i18n/pt_BR.po
odoo/addons/l10n_es_partner_mercantil/i18n/sl.po
odoo/addons/l10n_es_partner_mercantil/models/__init__.py
odoo/addons/l10n_es_partner_mercantil/models/partner_es.py
odoo/addons/l10n_es_partner_mercantil/readme/CONTRIBUTORS.rst
odoo/addons/l10n_es_partner_mercantil/readme/DESCRIPTION.rst
odoo/addons/l10n_es_partner_mercantil/readme/USAGE.rst
odoo/addons/l10n_es_partner_mercantil/static/description/icon.png
odoo/addons/l10n_es_partner_mercantil/static/description/icon.svg
odoo/addons/l10n_es_partner_mercantil/static/description/index.html
odoo/addons/l10n_es_partner_mercantil/views/res_partner_view.xml
odoo14_addon_l10n_es_partner_mercantil-14.0.1.0.1.dev7.dist-info/METADATA
odoo14_addon_l10n_es_partner_mercantil-14.0.1.0.1.dev7.dist-info/WHEEL
odoo14_addon_l10n_es_partner_mercantil-14.0.1.0.1.dev7.dist-info/top_level.txt
odoo14_addon_l10n_es_partner_mercantil-14.0.1.0.1.dev7.dist-info/RECORD
